tftest.py
tftest-1.8.5.dist-info/LICENSE
tftest-1.8.5.dist-info/METADATA
tftest-1.8.5.dist-info/WHEEL
tftest-1.8.5.dist-info/top_level.txt
tftest-1.8.5.dist-info/RECORD
