Metadata-Version: 2.1
Name: tftest
Version: 1.8.5
Summary: Simple Terraform test helper
Home-page: https://github.com/GoogleCloudPlatform/terraform-python-testing-helper
Author: Ludovico Magnocavallo
Author-email: ludomagno@google.com
Classifier: Programming Language :: Python :: 3
Classifier: License :: OSI Approved :: Apache Software License
Classifier: Operating System :: OS Independent
License-File: LICENSE
